<xml xmlns="http://www.w3.org/1999/xhtml">
  <block type="controls_repeat" id="186" inline="true" x="272" y="-44">
    <value name="TIMES">
      <block type="math_number" id="200">
        <field name="NUM">8</field>
      </block>
    </value>
    <statement name="DO">
      <block type="movement_forward" id="84">
        <next>
          <block type="robot_delay" id="95" inline="true">
            <value name="DELAY">
              <block type="math_number" id="102">
                <field name="NUM">100</field>
              </block>
            </value>
            <next>
              <block type="movement_left" id="123"></block>
            </next>
          </block>
        </next>
      </block>
    </statement>
    <next>
      <block type="controls_repeat" id="427" inline="true">
        <value name="TIMES">
          <block type="math_number" id="434">
            <field name="NUM">20</field>
          </block>
        </value>
        <statement name="DO">
          <block type="oled_cleardisplay" id="10">
            <next>
              <block type="oled_setcursor" id="27" inline="true">
                <value name="STARTX">
                  <block type="math_number" id="34">
                    <field name="NUM">10</field>
                  </block>
                </value>
                <value name="STARTY">
                  <block type="math_number" id="48">
                    <field name="NUM">10</field>
                  </block>
                </value>
                <next>
                  <block type="oled_drawtext" id="74">
                    <field name="TEXT">I LOVE MY MOMMYS</field>
                    <next>
                      <block type="led_select" id="215" inline="true">
                        <field name="ACTION">FLASH</field>
                        <value name="LED">
                          <block type="math_number" id="236">
                            <field name="NUM">0</field>
                          </block>
                        </value>
                        <next>
                          <block type="led_select" id="247" inline="true">
                            <field name="ACTION">ON</field>
                            <value name="LED">
                              <block type="math_number" id="284">
                                <field name="NUM">1</field>
                              </block>
                            </value>
                            <next>
                              <block type="led_select" id="258" inline="true">
                                <field name="ACTION">ON</field>
                                <value name="LED">
                                  <block type="math_number" id="324">
                                    <field name="NUM">2</field>
                                  </block>
                                </value>
                                <next>
                                  <block type="led_select" id="333" inline="true">
                                    <field name="ACTION">ON</field>
                                    <value name="LED">
                                      <block type="math_number" id="367">
                                        <field name="NUM">3</field>
                                      </block>
                                    </value>
                                    <next>
                                      <block type="led_select" id="351" inline="true">
                                        <field name="ACTION">ON</field>
                                        <value name="LED">
                                          <block type="math_number" id="374">
                                            <field name="NUM">4</field>
                                          </block>
                                        </value>
                                        <next>
                                          <block type="led_select" id="360" inline="true">
                                            <field name="ACTION">ON</field>
                                            <value name="LED">
                                              <block type="math_number" id="381">
                                                <field name="NUM">5</field>
                                              </block>
                                            </value>
                                            <next>
                                              <block type="robot_delay" id="270" inline="true">
                                                <value name="DELAY">
                                                  <block type="math_number" id="311">
                                                    <field name="NUM">100</field>
                                                  </block>
                                                </value>
                                              </block>
                                            </next>
                                          </block>
                                        </next>
                                      </block>
                                    </next>
                                  </block>
                                </next>
                              </block>
                            </next>
                          </block>
                        </next>
                      </block>
                    </next>
                  </block>
                </next>
              </block>
            </next>
          </block>
        </statement>
        <next>
          <block type="movement_stop" id="444"></block>
        </next>
      </block>
    </next>
  </block>
</xml>